README.rst
setup.cfg
setup.py
Tab_Data.egg-info/PKG-INFO
Tab_Data.egg-info/SOURCES.txt
Tab_Data.egg-info/dependency_links.txt
Tab_Data.egg-info/requires.txt
Tab_Data.egg-info/top_level.txt
tab_data/__init__.py
tab_data/preprocess.py