Metadata-Version: 2.1
Name: Tab-Data
Version: 0.1
Summary: Tab-data is a Python module for tabular data preprocessing based on Pandas.
Home-page: https://github.com/statmlben/tab-data
Author: Ben Dai
Author-email: bdai@umn.edu
License: MIT
Platform: UNKNOWN
